{
  "url": "http://sonichu.com/cwcki/Son_of_the_Miscreants",
  "title": "The Sons of the Miscreants chats",
  "display_title": "The Sons of the Miscreants chats",
  "html_content": "<div class=\"mw-body-content mw-content-ltr\" dir=\"ltr\" id=\"mw-content-text\" lang=\"en\"><div class=\"mw-parser-output\"><div class=\"redirectMsg\"><p>Redirect to:</p><ul class=\"redirectText\"><li><a href=\"/cwcki/The_Sons_of_the_Miscreants\" title=\"The Sons of the Miscreants\">The Sons of the Miscreants</a></li></ul></div>\n<!-- \nNewPP limit report\nCached time: 20251127054120\nCache expiry: 86400\nReduced expiry: false\nComplications: []\nCPU time usage: 0.000 seconds\nReal time usage: 0.000 seconds\nPreprocessor visited node count: 0/1000000\nPost‐expand include size: 0/2097152 bytes\nTemplate argument size: 0/2097152 bytes\nHighest expansion depth: 0/40\nExpensive parser function count: 0/100\nUnstrip recursion depth: 0/20\nUnstrip post‐expand size: 0/5000000 bytes\n-->\n<!--\nTransclusion expansion time report (%,ms,calls,template)\n100.00%    0.000      1 -total\n-->\n<!-- Saved in parser cache with key cwcki-1_:pcache:idhash:36370-0!canonical and timestamp 20251127054120 and revision id 303659. Serialized with JSON.\n -->\n</div>\n<div class=\"printfooter\">Retrieved from \"<a dir=\"ltr\" href=\"http://sonichu.com/w/index.php?title=The_Sons_of_the_Miscreants_chats&amp;oldid=303659\">http://sonichu.com/w/index.php?title=The_Sons_of_the_Miscreants_chats&amp;oldid=303659</a>\"</div></div>",
  "categories": [],
  "links": [
    "The Sons of the Miscreants"
  ],
  "scraped_at": "2025-11-26T21:41:22.994265"
}